Metadata-Version: 2.1
Name: forcats-py
Version: 0.0.1
Summary: Tools for working with pandas categoricals
Home-page: https://github.com/machow/forcats-py
Author: Michael Chow
Author-email: mc_al_github@fastmail.com
License: UNKNOWN
Platform: UNKNOWN
